[
  {
    "order": 1,
    "slug": "tpe-vs-silicone-sex-dolls",
    "title": "TPE vs Silicone Sex Dolls: Which Material Should You Choose?",
    "primaryKeyword": "silicone vs tpe",
    "author": "jesse",
    "category": "Materials And Care",
    "path": "content/learn/drafts/tpe-vs-silicone-sex-dolls.md"
  },
  {
    "order": 2,
    "slug": "sex-doll-cost",
    "title": "How Much Does a Sex Doll Cost? A Practical Price Guide",
    "primaryKeyword": "sex doll cost",
    "author": "alex",
    "category": "Buying Guides",
    "path": "content/learn/drafts/sex-doll-cost.md"
  },
  {
    "order": 3,
    "slug": "best-sex-dolls",
    "title": "Best Sex Dolls: How To Compare Models Before Buying",
    "primaryKeyword": "best sex dolls",
    "author": "alex",
    "category": "Buying Guides",
    "path": "content/learn/drafts/best-sex-dolls.md"
  },
  {
    "order": 4,
    "slug": "most-realistic-sex-dolls",
    "title": "Most Realistic Sex Dolls: What Actually Makes One Realistic?",
    "primaryKeyword": "most realistic sex dolls",
    "author": "alex",
    "category": "Buying Guides",
    "path": "content/learn/drafts/most-realistic-sex-dolls.md"
  },
  {
    "order": 5,
    "slug": "mini-sex-dolls",
    "title": "Mini Sex Dolls And Petite Sex Dolls: Size, Storage, And Fit",
    "primaryKeyword": "mini sex dolls",
    "author": "alex",
    "category": "Buying Guides",
    "path": "content/learn/drafts/mini-sex-dolls.md"
  },
  {
    "order": 6,
    "slug": "male-sex-doll-buying-guide",
    "title": "Male Sex Doll Buying Guide",
    "primaryKeyword": "male sex doll",
    "author": "alex",
    "category": "Buying Guides",
    "path": "content/learn/drafts/male-sex-doll-buying-guide.md"
  },
  {
    "order": 7,
    "slug": "sex-doll-reviews",
    "title": "How To Read Sex Doll Reviews Without Getting Fooled",
    "primaryKeyword": "sex doll review",
    "author": "jesse",
    "category": "Scams And Buyer Protection",
    "path": "content/learn/drafts/sex-doll-reviews.md"
  },
  {
    "order": 8,
    "slug": "ready-to-ship-vs-custom-sex-dolls",
    "title": "Ready-To-Ship vs Custom Sex Dolls",
    "primaryKeyword": "ready to ship sex dolls",
    "author": "alex",
    "category": "Shipping And Privacy",
    "path": "content/learn/drafts/ready-to-ship-vs-custom-sex-dolls.md"
  },
  {
    "order": 9,
    "slug": "discreet-sex-doll-shipping",
    "title": "How Discreet Sex Doll Shipping Works",
    "primaryKeyword": "discreet sex doll shipping",
    "author": "jesse",
    "category": "Shipping And Privacy",
    "path": "content/learn/drafts/discreet-sex-doll-shipping.md"
  }
]